datasmartly_cat/__init__.py
datasmartly_cat/cat.py
datasmartly_cat/bin/AWSSDK.Core.dll
datasmartly_cat/bin/AWSSDK.S3.dll
datasmartly_cat/bin/Apache.Arrow.dll
datasmartly_cat/bin/AppSoftware.LicenceEngine.Common.dll
datasmartly_cat/bin/AppSoftware.LicenceEngine.KeyVerification.dll
datasmartly_cat/bin/Autofac.dll
datasmartly_cat/bin/AutofacSerilogIntegration.dll
datasmartly_cat/bin/Azure.Core.dll
datasmartly_cat/bin/Azure.Identity.dll
datasmartly_cat/bin/Azure.Storage.Blobs.dll
datasmartly_cat/bin/Azure.Storage.Common.dll
datasmartly_cat/bin/BouncyCastle.Cryptography.dll
datasmartly_cat/bin/DuckDB.NET.Bindings.dll
datasmartly_cat/bin/DuckDB.NET.Data.dll
datasmartly_cat/bin/EPPlus.dll
datasmartly_cat/bin/Google.Api.Gax.Rest.dll
datasmartly_cat/bin/Google.Api.Gax.dll
datasmartly_cat/bin/Google.Apis.Auth.PlatformServices.dll
datasmartly_cat/bin/Google.Apis.Auth.dll
datasmartly_cat/bin/Google.Apis.Core.dll
datasmartly_cat/bin/Google.Apis.Storage.v1.dll
datasmartly_cat/bin/Google.Apis.dll
datasmartly_cat/bin/Google.Cloud.Storage.V1.dll
datasmartly_cat/bin/Humanizer.dll
datasmartly_cat/bin/JC.Cat.Core.Utils.dll
datasmartly_cat/bin/JC.Cat.Core.Utils.pdb
datasmartly_cat/bin/JC.Cat.Core.deps.json
datasmartly_cat/bin/JC.Cat.Core.dll
datasmartly_cat/bin/JC.Cat.Core.pdb
datasmartly_cat/bin/Microsoft.Bcl.AsyncInterfaces.dll
datasmartly_cat/bin/Microsoft.Data.SqlClient.SNI.dll
datasmartly_cat/bin/Microsoft.Data.SqlClient.dll
datasmartly_cat/bin/Microsoft.Extensions.Configuration.Abstractions.dll
datasmartly_cat/bin/Microsoft.Extensions.Configuration.FileExtensions.dll
datasmartly_cat/bin/Microsoft.Extensions.Configuration.Json.dll
datasmartly_cat/bin/Microsoft.Extensions.Configuration.dll
datasmartly_cat/bin/Microsoft.Extensions.DependencyInjection.Abstractions.dll
datasmartly_cat/bin/Microsoft.Extensions.DependencyInjection.dll
datasmartly_cat/bin/Microsoft.Extensions.FileProviders.Abstractions.dll
datasmartly_cat/bin/Microsoft.Extensions.FileProviders.Physical.dll
datasmartly_cat-1.16.5.dist-info/METADATA
datasmartly_cat-1.16.5.dist-info/WHEEL
datasmartly_cat-1.16.5.dist-info/top_level.txt
datasmartly_cat-1.16.5.dist-info/RECORD
