Metadata-Version: 2.4
Name: datasmartly_cat
Version: 1.16.5
Summary: CAT is a very simple tool that helps you automate tests for your data.
Project-URL: Homepage, https://justcat.it
Project-URL: Documentation, https://docs.justcat.it
Project-URL: Issues, https://board.usersnap.com/w6712lQ2m1uRDnc7#/
Project-URL: Changelog, https://docs.justcat.it/docs/release-notes/recent/
Classifier: Programming Language :: Python :: 3
Classifier: Operating System :: OS Independent
Requires-Dist: pythonnet
